image_collect.py
image_collect-0.0.4.dist-info/METADATA
image_collect-0.0.4.dist-info/WHEEL
image_collect-0.0.4.dist-info/top_level.txt
image_collect-0.0.4.dist-info/RECORD
