Metadata-Version: 2.1
Name: image_collect
Version: 0.0.4
Home-page: https://github.com/ohS0eek4/image-collect
Requires-Dist: BeautifulSoup4
Requires-Dist: deep-translator
